evolution_langchain/__init__.py
evolution_langchain/evolution_inference.py
evolution_langchain-1.0.0.dist-info/METADATA
evolution_langchain-1.0.0.dist-info/WHEEL
evolution_langchain-1.0.0.dist-info/licenses/LICENSE
evolution_langchain-1.0.0.dist-info/RECORD
